false_notice_analyzer/__init__.py
false_notice_analyzer/main.py
false_notice_analyzer/prompts.py
false_notice_analyzer-2025.12.21084504.dist-info/METADATA
false_notice_analyzer-2025.12.21084504.dist-info/WHEEL
false_notice_analyzer-2025.12.21084504.dist-info/top_level.txt
false_notice_analyzer-2025.12.21084504.dist-info/RECORD
