Metadata-Version: 2.4
Name: false-notice-analyzer
Version: 2025.12.21084504
Summary: A new package designed to streamline the process of identifying, extracting, and organizing information related to false notices filed against companies like Flock and Cyble Inc. It takes user inputs 
Author-email: false-notice-analyzer <hi@eugene.plus>
License: MIT
Project-URL: Homepage, https://github.com/chigwell/false-notice-analyzer
Requires-Python: >=3.9
Requires-Dist: langchain-llm7>=0.0.0
Requires-Dist: llmatch-messages>=0.0.0
Requires-Dist: langchain-core>=0.3.0
